redisgrpc/__init__.py
redisgrpc/redisgrpc.py
redisgrpc/redisgrpc_pb2.py
redisgrpc/redisgrpc_pb2.pyi
redisgrpc/redisgrpc_pb2_grpc.py
redisgrpc-0.4.dist-info/LICENSE
redisgrpc-0.4.dist-info/METADATA
redisgrpc-0.4.dist-info/WHEEL
redisgrpc-0.4.dist-info/top_level.txt
redisgrpc-0.4.dist-info/RECORD
