Metadata-Version: 2.1
Name: redisgrpc
Version: 0.4
Summary: A small production ready client library that emulates redis and used gRPC for communication
Home-page: https://github.com/gautam-sharma1/redisgrpc
Author: Gautam Sharma
Author-email: gautamsharma2813@gmail.com
Keywords: redis,gRPC
Classifier: Intended Audience :: Developers
Classifier: Topic :: Software Development :: Build Tools
Classifier: Programming Language :: Python :: 3
Classifier: License :: OSI Approved :: MIT License
Classifier: Operating System :: OS Independent
License-File: LICENSE
Requires-Dist: grpcio-tools
